Metadata-Version: 2.1
Name: Pyprintery
Version: 1.0.0
Summary: Simulates a game window built by the terminal console, Simple word games can be developed, Third-party libraries that are more entertaining than useful, Suitable for Python beginners
Home-page: UNKNOWN
License: UNKNOWN
Platform: UNKNOWN
